line_formater/__init__.py
line_formater/line_formater.py
line_formater-1.1.0.dist-info/DESCRIPTION.rst
line_formater-1.1.0.dist-info/METADATA
line_formater-1.1.0.dist-info/RECORD
line_formater-1.1.0.dist-info/WHEEL
line_formater-1.1.0.dist-info/metadata.json
line_formater-1.1.0.dist-info/top_level.txt
line_formater-1.1.0.dist-info/zip-safe
