Metadata-Version: 2.0
Name: line-formater
Version: 1.1.0
Summary: A collection of line text formaters
Home-page: https://github.com/bclmary/line_formater.git
Maintainer: BCL Mary
Maintainer-email: bclmary@mailoo.org
License: GPL-3.0+
Keywords: line text format formating formater align center justify columns
Platform: any
Classifier: Development Status :: 5 - Production/Stable
Classifier: License :: OSI Approved :: GNU General Public License v3 or later (GPLv3+)
Classifier: Natural Language :: English
Classifier: Environment :: Console
Classifier: Programming Language :: Python :: 2
Classifier: Programming Language :: Python :: 3
Classifier: Intended Audience :: Developers
Classifier: Operating System :: POSIX
Classifier: Operating System :: POSIX :: Linux
Classifier: Operating System :: Microsoft :: Windows
Classifier: Operating System :: Microsoft :: Windows :: Windows 7
Classifier: Operating System :: Microsoft :: Windows :: Windows 10
Classifier: Topic :: Utilities
Requires-Python: >=2.7
